delegable/__init__.py
delegable/delegable.py
tasks/__init__.py
delegable-0.0.5.dist-info/LICENSE.md
delegable-0.0.5.dist-info/METADATA
delegable-0.0.5.dist-info/WHEEL
delegable-0.0.5.dist-info/top_level.txt
delegable-0.0.5.dist-info/RECORD
