Metadata-Version: 2.1
Name: delegable
Version: 0.0.5
Summary: Delegable is a simple Python alternative to Ruby on Rails' delegate module.
Home-page: https://github.com/suzukimilanpaak/delegable
Author: suzukimilanpaak
Author-email: sin.wave808@gmail.com
License: MIT
Keywords: delegate delegates delegable delegation ruby rails
Platform: UNKNOWN
Classifier: Intended Audience :: Developers
Classifier: License :: OSI Approved :: MIT License
Classifier: Programming Language :: Python
Classifier: Programming Language :: Python :: 3
Classifier: Programming Language :: Python :: 3.5
Classifier: Programming Language :: Python :: 3.6
Classifier: Programming Language :: Python :: 3.7
Classifier: Programming Language :: Python :: 3.8
Requires-Dist: setuptools (>=0.7)
Provides-Extra: testing
Requires-Dist: flake8 (==3.8.2) ; extra == 'testing'
Requires-Dist: pytest (==5.4.3) ; extra == 'testing'
Requires-Dist: pytest-cov (==2.9.0) ; extra == 'testing'
Requires-Dist: pytest-flake8 (==1.0.6) ; extra == 'testing'
Requires-Dist: pytest-mock (==3.1.0) ; extra == 'testing'
Requires-Dist: pytest-describe (==1.0.0) ; extra == 'testing'
